merge_dictionaries-0.4.1.data/scripts/merge-dictionaries
merge_dictionaries-0.4.1.dist-info/licenses/LICENSE
mergedictionaries/__init__.py
mergedictionaries/actions/__init__.py
mergedictionaries/actions/delete_words.py
mergedictionaries/app/__init__.py
mergedictionaries/app/app.py
mergedictionaries/output/__init__.py
mergedictionaries/output/jetbrains.py
mergedictionaries/sources/__init__.py
mergedictionaries/sources/git.py
mergedictionaries/sources/hunspell.py
mergedictionaries/sources/jetbrains.py
mergedictionaries/utils/__init__.py
mergedictionaries/utils/collections.py
mergedictionaries/write/__init__.py
mergedictionaries/write/git.py
mergedictionaries/write/jetbrains.py
merge_dictionaries-0.4.1.dist-info/METADATA
merge_dictionaries-0.4.1.dist-info/WHEEL
merge_dictionaries-0.4.1.dist-info/top_level.txt
merge_dictionaries-0.4.1.dist-info/RECORD
