Metadata-Version: 2.4
Name: merge-dictionaries
Version: 0.4.1
Summary: Merge dictionaries
Home-page: https://devcentral.nasqueron.org/source/merge-dictionaries/
Author: Sébastien Santoro
Author-email: dereckson@espace-win.org
License: BSD-2-Clause
Project-URL: Bug Tracker, https://devcentral.nasqueron.org/tag/development_tools/
Classifier: Programming Language :: Python :: 3
Classifier: License :: OSI Approved :: BSD License
Classifier: Operating System :: OS Independent
Classifier: Environment :: Console
Classifier: Intended Audience :: Developers
Classifier: Topic :: Software Development :: Build Tools
Requires-Python: >=3.7
License-File: LICENSE
Requires-Dist: PyYAML<7.0,>=6.0
Dynamic: license-file
